Project7/CPU/CPU.vhdl
library IEEE;
use IEEE.STD_LOGIC_1164.ALL;

entity Mux3Way8Bit is
    port (
        sel : in std_logic_vector(1 downto 0); -- 2-bit select signal
        a   : in std_logic_vector(7 downto 0); -- 8-bit input a
        b   : in std_logic_vector(7 downto 0); -- 8-bit input b
        c   : in std_logic_vector(7 downto 0); -- 8-bit input c
        y   : out std_logic_vector(7 downto 0) -- 8-bit output y
    );
end Mux3Way8Bit;

architecture Behavioral of Mux3Way8Bit is
begin
    process(sel, a, b, c)
    begin
        case sel is
            when "00" =>
                y <= a;
            when "01" =>
                y <= b;
            when "10" =>
                y <= c;
            when others =>
                y <= (others => '0'); -- default case to handle unused state
        end case;
    end process;
end Behavioral;



library IEEE;
use IEEE.std_logic_1164.all;
use IEEE.numeric_std.all;

entity CPU is
	port (
		status    : out std_ulogic;
		CheckRAM  : out std_logic_vector(7 downto 0);
		CheckALU  : out std_logic_vector(7 downto 0);
		clk       : in std_ulogic;
		out1      : out std_logic_vector(7 downto 0);
		out2      : out std_logic_vector(7 downto 0);
		in1       : out std_logic_vector(7 downto 0)
	);
end CPU;

architecture behave of CPU is
	component ALU16
		port (
			a      : in std_logic_vector(7 downto 0);
			b      : in std_logic_vector(7 downto 0);
			opcode : in std_logic_vector(3 downto 0);
			V      : out std_ulogic;
			N      : out std_ulogic;
			Z      : out std_ulogic;
			C      : out std_ulogic;
			result : out std_logic_vector(7 downto 0)
		);
	end component;
	
	component RAM128
		port (
			input   : in std_logic_vector(7 downto 0);
			output  : out std_logic_vector(7 downto 0);
			address : in std_logic_vector(2 downto 0);
			load    : in std_ulogic;
			clk     : in std_ulogic
		);
	end component;
	
	component RAM8
		port (
			input    : in std_logic_vector(7 downto 0);
			output1  : out std_logic_vector(7 downto 0);
			output2  : out std_logic_vector(7 downto 0);
			address  : in std_logic_vector(2 downto 0);
			load     : in std_ulogic;
			address1 : in std_logic_vector(2 downto 0);
			address2 : in std_logic_vector(2 downto 0);
			clk      : in std_ulogic
		);
	end component;
	
	component Mux3Way8Bit
		port (
			sel : in std_logic_vector(1 downto 0); -- 2-bit select signal
			a   : in std_logic_vector(7 downto 0); -- 8-bit input a
			b   : in std_logic_vector(7 downto 0); -- 8-bit input b
			c   : in std_logic_vector(7 downto 0); -- 8-bit input c
			y   : out std_logic_vector(7 downto 0) -- 8-bit output y
		);
	end component;
	
	type instruction is array (0 to 7) of std_logic_vector(15 downto 0);
	signal ins : instruction  := ("0110000110110101", "0110000100100110", "0010110111101110", "1000000010100111",
	"0000000000000000", "0000000000000000", "0000000000000000", "0000000000000000");
	
	signal i : integer := 0;
	signal ld, st : std_ulogic;
	signal op : std_logic_vector(15 downto 0);
	signal reg, resultALU, muxed, resultRAM, o1, o2 : std_logic_vector(7 downto 0);
	signal addr, addr1, addr2 : std_logic_vector(2 downto 0) := "000";
	signal mem : std_logic_vector(2 downto 0) := "000";
	signal code : std_logic_vector(3 downto 0) := "1111";
	signal x : std_logic_vector(1 downto 0) := "11";
	
	signal statusN, statusV, statusC, statusZ : std_ulogic; 
	
begin
	process (clk)
	begin
		if rising_edge(clk) then
			op <= ins(i);
			i <= i + 1;
			if (op(15) = '0' and op(14) = '1' and op(13) = '1') then
				-- Load value directly
				ld <= '1';
				st <= '0';
				reg <= op(10 downto 3);
				addr <= op(2 downto 0);
				x <= "00";
			elsif (op(15) = '0' and op(14) = '1' and op(13) = '0') then
				-- Load from memory
				ld <= '1';
				st <= '0';
				mem <= op(5 downto 3);
				addr <= op(2 downto 0);
				x <= "01";
			elsif (op(15) = '1' and op(14) = '0' and op(13) = '0') then
				-- Store
				ld <= '0';
				st <= '1';
				mem <= op(5 downto 3);
				addr1 <= op(2 downto 0);
			elsif (op(15) = '0' and op(14) = '0' and op(13) = '1') then
				-- Operation
				ld <= '1';
				st <= '0';
				code <= op(12 downto 9);
				addr1 <= op(5 downto 3);
				addr2 <= op(2 downto 0);
				addr <= op(8 downto 6);
				x <= "10";
			else
				ld <= '0';
				st <= '0';
			end if;
		end if;
	end process;
	
	RegisterBank : RAM8 port map(
		input => muxed,
		output1 => o1,
		output2 => o2,
		address => addr,
		load => ld,
		address1 => addr1,
		address2 => addr2,
		clk => clk
	);
	
	ALU : ALU16 port map (
		a => o1,
		b => o2,
		opcode => code,
		V => statusV,
		N => statusN,
		Z => statusZ,
		C => statusC,
		result => resultALU
	);
	
	RAM : RAM128 port map (
		input => o1,
		output => resultRAM,
		address => mem,
		load => st,
		clk => clk
	);
	
	Mux : Mux3Way8Bit port map (
		sel => x,
		a => reg,
		b => resultRAM,
		c => resultALU,
		y => muxed
	);
	
	status <= statusN or statusV or statusZ or statusC;
	CheckRAM <= resultRAM;
	CheckALU <= resultALU;
	out1 <= o1;
	out2 <= o2;
	in1 <= muxed;
	
end behave;

Project7/CPU/RAM128.vhdl
library IEEE;
use IEEE.std_logic_1164.all;

entity dlatch2 is
	port (
		d : in std_ulogic;
		e : in std_ulogic;
		q : out std_ulogic
	);
end dlatch2;

architecture behave of dlatch2 is
begin
	process (e)
	begin
	
	if e = '0' then
		q <= d;
	end if;
	end process;
end behave;



library IEEE;
use IEEE.std_logic_1164.all;

entity dff2 is
	port (
		d   : in std_ulogic;
		clk : in std_ulogic;
		clr : in std_ulogic;
		q   : out std_ulogic
		);
end dff2;


architecture behave of dff2 is
	signal q1, clk_temp, q2 : std_ulogic;
	
	component dlatch2
		port (
			d : in std_ulogic;
			e : in std_ulogic;
			q : out std_ulogic
		);
	end component;
	
begin
	clk_temp <= not clk;
	Master : dlatch2
		port map (
			d => d,
			e => clk_temp,
			q => q1
		);
	Slave : dlatch2
		port map (
			d => q1,
			e => clk,
			q => q2
		);
	q <= q2 and clr;
end behave;


library IEEE;
use IEEE.std_logic_1164.all;

entity bit_reg is
	generic (
		clr : std_logic := '1'
	);
	port (
		inp  : in std_ulogic;
		load : in std_ulogic;
		outp : out std_ulogic
	);
end bit_reg;

architecture behave of bit_reg is
	component dff2
		port (
			d   : in std_ulogic;
			clk : in std_ulogic;
			clr : in std_ulogic;
			q   : out std_ulogic
		);
	end component;
	
begin
	reg : dff2 port map (d => inp, clk => load, clr => clr, q => outp);
end behave;



library IEEE;
use IEEE.std_logic_1164.all;

entity reg8 is
	port (
		load : in std_ulogic;
		inp  : in std_logic_vector(7 downto 0);
		outp : out std_logic_vector(7 downto 0)
	);
end entity;


architecture behave of reg8 is
	component bit_reg
		port (
			inp  : in std_ulogic;
			load : in std_ulogic;
			outp : out std_ulogic
		);
	end component;
	
begin
	gen_reg : for i in 0 to 7 generate
		register8 : bit_reg port map (inp => inp(i), outp => outp(i), load => load);
	end generate;
end behave;



library IEEE;
use IEEE.std_logic_1164.all;
use IEEE.numeric_std.all;

entity RAM128 is
	port (
		input   : in std_logic_vector(7 downto 0);
		output  : out std_logic_vector(7 downto 0);
		address : in std_logic_vector(2 downto 0);
		load    : in std_ulogic;
		clk     : in std_ulogic
 	);
end entity;


architecture behave of RAM128 is
	
	type mem is array (0 to 7) of std_logic_vector(7 downto 0);
	signal memory : mem  := ("00000000", "00000000", "00000000", "00000000",
	"00000000", "00000000", "00000000", "00000000");
	
begin
	pro1 : process (load, address, clk)
		variable i : integer;
	begin
		i := to_integer(unsigned(address));
		if load = '1' then
			memory(i) <= input;
		else
			output <= memory(i);
		end if;
	end process;
end architecture;

	--gen_ram : for i in 0 to 7 generate
		--ram : reg16 port map (inp => input((15+16*i) downto 16*i), outp => outp(i), load => load);
	--end generate;

Project7/CPU/ALU16.vhdl
library ieee;
use ieee.std_logic_1164.all;

entity mux is
	port (
		a : in std_logic_vector(7 downto 0);
		sel_1 : in std_ulogic;
		out1 : out std_logic_vector(7 downto 0)
	);
end entity;

architecture behaviour of mux is
begin
	out1 <= a when sel_1 = '0' else not a;
end behaviour;



library ieee;
use ieee.std_logic_1164.all;

entity lu is
	port (
		a : in std_logic_vector(7 downto 0);
		b : in std_logic_vector(7 downto 0);
		sel_1 : in std_ulogic;
		sel_2 : in std_ulogic;
		out_lu : out std_logic_vector(7 downto 0)
	);
end entity;

architecture behaviour of lu is
begin
	process(a, b, sel_1, sel_2)
	begin
		if (sel_1 = '0' and sel_2 = '0') then
			out_lu <= a and b;
		elsif (sel_1 = '1' and sel_2 = '0') then
			out_lu <= a or b;
		elsif (sel_1 = '0' and sel_2 = '1') then
			out_lu <= a xor b;
		else
			out_lu <= b;
		end if;
	end process;
end behaviour;


library ieee;
use ieee.std_logic_1164.all;

entity full is
	port (
		a : in std_ulogic;
		b : in std_ulogic;
		cin : in std_ulogic;
		cout : out std_ulogic;
		sum : out std_ulogic
	);
end entity;

architecture behaviour of full is
begin
	sum <= a xor b xor cin;
	cout <= ((a xor b) and cin) or (a and b);
end behaviour;


library ieee;
use ieee.std_logic_1164.all;

entity au is
	port (
		a : in std_logic_vector(7 downto 0);
		b : in std_logic_vector(7 downto 0);
		cin : in std_ulogic;
		v : out std_ulogic;
		c : out std_ulogic;
		out_au : out std_logic_vector(7 downto 0)
	);
end entity;

architecture behaviour of au is
	signal c1, c2, c3, c4, c5, c6, c7, c8 : std_ulogic;
	
	component full
		port (
			a : in std_ulogic;
			b : in std_ulogic;
			cin : in std_ulogic;
			cout : out std_ulogic;
			sum : out std_ulogic
		);
	end component;
begin
	U1 : full port map (a => a(0), b => b(0), cin => cin, sum => out_au(0), cout => c1);
	U2 : full port map (a => a(1), b => b(1), cin => c1, sum => out_au(1), cout => c2);
	U3 : full port map (a => a(2), b => b(2), cin => c2, sum => out_au(2), cout => c3);
	U4 : full port map (a => a(3), b => b(3), cin => c3, sum => out_au(3), cout => c4);
	U5 : full port map (a => a(4), b => b(4), cin => c4, sum => out_au(4), cout => c5);
	U6 : full port map (a => a(5), b => b(5), cin => c5, sum => out_au(5), cout => c6);
	U7 : full port map (a => a(6), b => b(6), cin => c6, sum => out_au(6), cout => c7);
	U8 : full port map (a => a(7), b => b(7), cin => c7, sum => out_au(7), cout => c8);
	c <= c8;
	v <= c8 xor c7;
end behaviour;


library ieee;
use ieee.std_logic_1164.all;

entity mux2 is
    port (
        in1  : in std_logic_vector(7 downto 0);
        in2  : in std_logic_vector(7 downto 0);
        sel  : in std_ulogic;
        out1 : out std_logic_vector(7 downto 0)
    );
end entity;

architecture behaviour of mux2 is
begin
    out1 <= in1 when sel='0' else in2;
end behaviour;



library ieee;
use ieee.std_logic_1164.all;

entity ALU16 is
	port (
		a      : in std_logic_vector(7 downto 0);
		b      : in std_logic_vector(7 downto 0);
		opcode : in std_logic_vector(3 downto 0);
		V      : out std_ulogic;
		N      : out std_ulogic;
		Z      : out std_ulogic;
		C      : out std_ulogic;
		result : out std_logic_vector(7 downto 0)
	);
end entity;

architecture behaviour of ALU16 is
	signal muxa, muxb, result_au, result_lu, resultx : std_logic_vector(7 downto 0);

	component au
		port (
			a : in std_logic_vector(7 downto 0);
			b : in std_logic_vector(7 downto 0);
			cin : in std_ulogic;
			v : out std_ulogic;
			c : out std_ulogic;
			out_au : out std_logic_vector(7 downto 0)
		);
	end component;
	
	component lu
		port (
			a : in std_logic_vector(7 downto 0);
			b : in std_logic_vector(7 downto 0);
			sel_1 : in std_ulogic;
			sel_2 : in std_ulogic;
			out_lu : out std_logic_vector(7 downto 0)
		);
	end component;
	
	component mux
		port (
			a : in std_logic_vector(7 downto 0);
			sel_1 : in std_ulogic;
			out1 : out std_logic_vector(7 downto 0)
		);
	end component;
	
	component mux2
        port (
            in1  : in std_logic_vector(7 downto 0);
            in2  : in std_logic_vector(7 downto 0);
            sel  : in std_ulogic;
            out1 : out std_logic_vector(7 downto 0)
        );
    end component;
	
begin
	U1 : mux port map (a => b, sel_1 => opcode(1), out1 => muxb);
	U2 : mux port map (a => a, sel_1 => opcode(0), out1 => muxa);
	U3 : au port map (a => muxa, b => muxb, cin => opcode(2), v => V, c => C, out_au => result_au);
	U4 : lu port map (a => a, b => muxb, sel_1 => opcode(0), sel_2 => opcode(2), out_lu => result_lu);
	U5 : mux2 port map (in1 => result_au, in2 => result_lu, sel => opcode(3), out1 => resultx);
	Z <= not(result_au(0) or result_au(1) or result_au(2) or result_au(3) or result_au(4) or result_au(5) or result_au(6) or result_au(7));
	N <= resultx(7);
	result <= resultx;
end behaviour;

Project7/CPU/RAM8.vhdl
library IEEE;
use IEEE.std_logic_1164.all;
use IEEE.numeric_std.all;

entity RAM8 is
	port (
		input   : in std_logic_vector(7 downto 0);
		output1  : out std_logic_vector(7 downto 0);
		output2 : out std_logic_vector(7 downto 0);
		address : in std_logic_vector(2 downto 0);
		load    : in std_ulogic;
		address1 : in std_logic_vector(2 downto 0);
		address2 : in std_logic_vector(2 downto 0);
		clk : in std_ulogic
 	);
end entity;


architecture behave of RAM8 is
	
	type mem is array (0 to 7) of std_logic_vector(7 downto 0);
	signal memory : mem  := ("00000000", "00000000", "00000000", "00000000", "00000000", "00000000", "00000000", "00000000");
	
begin
	
	output1 <= memory(to_integer(unsigned(address1)));
	output2 <= memory(to_integer(unsigned(address2)));
	
	pro1 : process (load, address, clk)
		variable i : integer;
	begin
		i := to_integer(unsigned(address));
		if load = '1' then
			memory(i) <= input;
		end if;
	end process;
end architecture;

Project7/CPU/CPU_tb.vhdl
library IEEE;
use IEEE.std_logic_1164.all;

entity CPU_tb is
end entity;

architecture test of CPU_tb is

	signal status, clk : std_ulogic;
	signal CheckRAM, CheckALU, out1, out2, in1 : std_logic_vector(7 downto 0);
	
	component CPU
		port (
			status    : out std_ulogic;
			CheckRAM  : out std_logic_vector(7 downto 0);
			CheckALU  : out std_logic_vector(7 downto 0);
			clk       : in std_ulogic;
			out1      : out std_logic_vector(7 downto 0);
			out2      : out std_logic_vector(7 downto 0);
			in1       : out std_logic_vector(7 downto 0)
		);
	end component;
	
begin
	
	UUT : CPU port map (status => status, CheckRAM => CheckRAM, CheckALU => CheckALU, clk => clk, out1 => out1, out2 => out2, in1 => in1);

	clk_process: process
    begin
        while true loop
			clk <= '0';
			wait for 10 ns;
			clk <= '1';
			wait for 10 ns;
        end loop;
    end process;
	
	test_process: process
    begin
		
		wait for 140 ns;
		
        -- End simulation
        assert false report "Simulation Ended" severity failure;
    end process;
end test;

Project7/CPU/CPU.vcd
$date
  Tue Jul 23 08:18:24 2024
$end
$version
  GHDL v0
$end
$timescale
  1 fs
$end
$scope module standard $end
$upscope $end
$scope module std_logic_1164 $end
$upscope $end
$scope module numeric_std $end
$upscope $end
$scope module cpu_tb $end
$var reg 1 ! status $end
$var reg 1 " clk $end
$var reg 8 # checkram[7:0] $end
$var reg 8 $ checkalu[7:0] $end
$var reg 8 % out1[7:0] $end
$var reg 8 & out2[7:0] $end
$var reg 8 ' in1[7:0] $end
$scope module uut $end
$var reg 1 ( status $end
$var reg 8 ) checkram[7:0] $end
$var reg 8 * checkalu[7:0] $end
$var reg 1 + clk $end
$var reg 8 , out1[7:0] $end
$var reg 8 - out2[7:0] $end
$var reg 8 . in1[7:0] $end
$comment ins is not handled $end
$var integer 32 / i $end
$var reg 1 0 ld $end
$var reg 1 1 st $end
$var reg 16 2 op[15:0] $end
$var reg 8 3 reg[7:0] $end
$var reg 8 4 resultalu[7:0] $end
$var reg 8 5 muxed[7:0] $end
$var reg 8 6 resultram[7:0] $end
$var reg 8 7 o1[7:0] $end
$var reg 8 8 o2[7:0] $end
$var reg 3 9 addr[2:0] $end
$var reg 3 : addr1[2:0] $end
$var reg 3 ; addr2[2:0] $end
$var reg 3 < mem[2:0] $end
$var reg 4 = code[3:0] $end
$var reg 2 > x[1:0] $end
$var reg 1 ? statusn $end
$var reg 1 @ statusv $end
$var reg 1 A statusc $end
$var reg 1 B statusz $end
$scope module registerbank $end
$var reg 8 C input[7:0] $end
$var reg 8 D output1[7:0] $end
$var reg 8 E output2[7:0] $end
$var reg 3 F address[2:0] $end
$var reg 1 G load $end
$var reg 3 H address1[2:0] $end
$var reg 3 I address2[2:0] $end
$var reg 1 J clk $end
$comment memory is not handled $end
$upscope $end
$scope module alu $end
$var reg 8 K a[7:0] $end
$var reg 8 L b[7:0] $end
$var reg 4 M opcode[3:0] $end
$var reg 1 N v $end
$var reg 1 O n $end
$var reg 1 P z $end
$var reg 1 Q c $end
$var reg 8 R result[7:0] $end
$var reg 8 S muxa[7:0] $end
$var reg 8 T muxb[7:0] $end
$var reg 8 U result_au[7:0] $end
$var reg 8 V result_lu[7:0] $end
$var reg 8 W resultx[7:0] $end
$scope module u1 $end
$var reg 8 X a[7:0] $end
$var reg 1 Y sel_1 $end
$var reg 8 Z out1[7:0] $end
$upscope $end
$scope module u2 $end
$var reg 8 [ a[7:0] $end
$var reg 1 \ sel_1 $end
$var reg 8 ] out1[7:0] $end
$upscope $end
$scope module u3 $end
$var reg 8 ^ a[7:0] $end
$var reg 8 _ b[7:0] $end
$var reg 1 ` cin $end
$var reg 1 a v $end
$var reg 1 b c $end
$var reg 8 c out_au[7:0] $end
$var reg 1 d c1 $end
$var reg 1 e c2 $end
$var reg 1 f c3 $end
$var reg 1 g c4 $end
$var reg 1 h c5 $end
$var reg 1 i c6 $end
$var reg 1 j c7 $end
$var reg 1 k c8 $end
$scope module u1 $end
$var reg 1 l a $end
$var reg 1 m b $end
$var reg 1 n cin $end
$var reg 1 o cout $end
$var reg 1 p sum $end
$upscope $end
$scope module u2 $end
$var reg 1 q a $end
$var reg 1 r b $end
$var reg 1 s cin $end
$var reg 1 t cout $end
$var reg 1 u sum $end
$upscope $end
$scope module u3 $end
$var reg 1 v a $end
$var reg 1 w b $end
$var reg 1 x cin $end
$var reg 1 y cout $end
$var reg 1 z sum $end
$upscope $end
$scope module u4 $end
$var reg 1 { a $end
$var reg 1 | b $end
$var reg 1 } cin $end
$var reg 1 !" cout $end
$var reg 1 "" sum $end
$upscope $end
$scope module u5 $end
$var reg 1 #" a $end
$var reg 1 $" b $end
$var reg 1 %" cin $end
$var reg 1 &" cout $end
$var reg 1 '" sum $end
$upscope $end
$scope module u6 $end
$var reg 1 (" a $end
$var reg 1 )" b $end
$var reg 1 *" cin $end
$var reg 1 +" cout $end
$var reg 1 ," sum $end
$upscope $end
$scope module u7 $end
$var reg 1 -" a $end
$var reg 1 ." b $end
$var reg 1 /" cin $end
$var reg 1 0" cout $end
$var reg 1 1" sum $end
$upscope $end
$scope module u8 $end
$var reg 1 2" a $end
$var reg 1 3" b $end
$var reg 1 4" cin $end
$var reg 1 5" cout $end
$var reg 1 6" sum $end
$upscope $end
$upscope $end
$scope module u4 $end
$var reg 8 7" a[7:0] $end
$var reg 8 8" b[7:0] $end
$var reg 1 9" sel_1 $end
$var reg 1 :" sel_2 $end
$var reg 8 ;" out_lu[7:0] $end
$upscope $end
$scope module u5 $end
$var reg 8 <" in1[7:0] $end
$var reg 8 =" in2[7:0] $end
$var reg 1 >" sel $end
$var reg 8 ?" out1[7:0] $end
$upscope $end
$upscope $end
$scope module ram $end
$var reg 8 @" input[7:0] $end
$var reg 8 A" output[7:0] $end
$var reg 3 B" address[2:0] $end
$var reg 1 C" load $end
$var reg 1 D" clk $end
$comment memory is not handled $end
$upscope $end
$scope module mux $end
$var reg 2 E" sel[1:0] $end
$var reg 8 F" a[7:0] $end
$var reg 8 G" b[7:0] $end
$var reg 8 H" c[7:0] $end
$var reg 8 I" y[7:0] $end
$upscope $end
$upscope $end
$upscope $end
$enddefinitions $end
#0
1!
0"
b00000000 #
b11111111 $
b00000000 %
b00000000 &
b00000000 '
1(
b00000000 )
b11111111 *
0+
b00000000 ,
b00000000 -
b00000000 .
b0 /
U0
U1
bUUUUUUUUUUUUUUUU 2
bUUUUUUUU 3
b11111111 4
b00000000 5
b00000000 6
b00000000 7
b00000000 8
b000 9
b000 :
b000 ;
b000 <
b1111 =
b11 >
1?
0@
1A
0B
b00000000 C
b00000000 D
b00000000 E
b000 F
UG
b000 H
b000 I
0J
b00000000 K
b00000000 L
b1111 M
0N
1O
0P
1Q
b11111111 R
b11111111 S
b11111111 T
b11111111 U
b11111111 V
b11111111 W
b00000000 X
1Y
b11111111 Z
b00000000 [
1\
b11111111 ]
b11111111 ^
b11111111 _
1`
0a
1b
b11111111 c
1d
1e
1f
1g
1h
1i
1j
1k
1l
1m
1n
1o
1p
1q
1r
1s
1t
1u
1v
1w
1x
1y
1z
1{
1|
1}
1!"
1""
1#"
1$"
1%"
1&"
1'"
1("
1)"
1*"
1+"
1,"
1-"
1."
1/"
10"
11"
12"
13"
14"
15"
16"
b00000000 7"
b11111111 8"
19"
1:"
b11111111 ;"
b11111111 <"
b11111111 ="
1>"
b11111111 ?"
b00000000 @"
b00000000 A"
b000 B"
UC"
0D"
b11 E"
bUUUUUUUU F"
b00000000 G"
b11111111 H"
b00000000 I"
#10000000
1"
1+
b1 /
00
01
b0110000110110101 2
0G
1J
0C"
1D"
#20000000
0"
0+
0J
0D"
#30000000
1"
b00110110 '
1+
b00110110 .
b10 /
10
b0110000100100110 2
b00110110 3
b00110110 5
b101 9
b00 >
b00110110 C
b101 F
1G
1J
1D"
b00 E"
b00110110 F"
b00110110 I"
#40000000
0"
0+
0J
0D"
#50000000
1"
b00100100 '
1+
b00100100 .
b11 /
b0010110111101110 2
b00100100 3
b00100100 5
b110 9
b00100100 C
b110 F
1J
1D"
b00100100 F"
b00100100 I"
#60000000
0"
0+
0J
0D"
#70000000
1"
b00010010 $
b00110110 %
b00100100 &
b00010010 '
b00010010 *
1+
b00110110 ,
b00100100 -
b00010010 .
b100 /
b1000000010100111 2
b00010010 4
b00010010 5
b00110110 7
b00100100 8
b111 9
b101 :
b110 ;
b0110 =
b10 >
0?
0B
b00010010 C
b00110110 D
b00100100 E
b111 F
b101 H
b110 I
1J
b00110110 K
b00100100 L
b0110 M
0O
0P
b00010010 R
b00110110 S
b11011011 T
b00010010 U
b11101101 V
b00010010 W
b00100100 X
b11011011 Z
b00110110 [
0\
b00110110 ]
b00110110 ^
b11011011 _
b00010010 c
0l
0p
1q
1u
1v
0w
0z
0{
0""
1#"
1'"
1("
0)"
0,"
0-"
01"
02"
06"
b00110110 7"
b11011011 8"
09"
b11101101 ;"
b00010010 <"
b11101101 ="
0>"
b00010010 ?"
b00110110 @"
1D"
b10 E"
b00010010 H"
b00010010 I"
#80000000
0"
0+
0J
0D"
#90000000
1!
1"
b11101110 $
b00010010 %
b11101110 '
1(
b11101110 *
1+
b00010010 ,
b11101110 .
b101 /
00
11
b0000000000000000 2
b11101110 4
b11101110 5
b00010010 7
b111 :
b100 <
1?
0@
0A
b11101110 C
b00010010 D
0G
b111 H
1J
b00010010 K
0N
1O
0Q
b11101110 R
b00010010 S
b11101110 U
b11001001 V
b11101110 W
b00010010 [
b00010010 ]
b00010010 ^
0a
0b
b11101110 c
0f
0g
0i
0j
0k
0v
0y
1z
0}
0!"
1""
0%"
0'"
0("
0+"
1,"
0/"
00"
11"
04"
05"
16"
b00010010 7"
b11001001 ;"
b11101110 <"
b11001001 ="
b11101110 ?"
b00010010 @"
b100 B"
1C"
1D"
b11101110 H"
b11101110 I"
#100000000
0"
0+
0J
0D"
#110000000
1"
b00010010 #
b00010010 )
1+
b110 /
01
b00010010 6
1J
b00010010 A"
0C"
1D"
b00010010 G"
#120000000
0"
0+
0J
0D"
#130000000
1"
1+
b111 /
1J
1D"
